{
  "$schema": "https://developer.microsoft.com/json-schemas/fabric/item/report/definition/visualContainer/2.7.0/schema.json",
  "name": "7653388957c64fdb197f",
  "position": {
    "x": 717,
    "y": 210,
    "z": 0,
    "height": 300,
    "width": 534,
    "tabOrder": 0
  },
  "visual": {
    "visualType": "tableEx",
    "query": {
      "queryState": {
        "Values": {
          "projections": [
            {
              "field": {
                "Column": {
                  "Expression": {
                    "SourceRef": {
                      "Entity": "protheus_contatos"
                    }
                  },
                  "Property": "estado_uf"
                }
              },
              "queryRef": "protheus_contatos.estado_uf",
              "nativeQueryRef": "estado_uf"
            },
            {
              "field": {
                "Measure": {
                  "Expression": {
                    "SourceRef": {
                      "Entity": "protheus_pedidosVendas"
                    }
                  },
                  "Property": "ATC Clientes por Estado"
                }
              },
              "queryRef": "protheus_pedidosVendas.ATC Clientes por Estado",
              "nativeQueryRef": "ATC Clientes por Estado"
            },
            {
              "field": {
                "Measure": {
                  "Expression": {
                    "SourceRef": {
                      "Entity": "protheus_pedidosVendas"
                    }
                  },
                  "Property": "ATC Faturamento Total"
                }
              },
              "queryRef": "protheus_pedidosVendas.ATC Faturamento Total",
              "nativeQueryRef": "ATC Faturamento Total"
            },
            {
              "field": {
                "Measure": {
                  "Expression": {
                    "SourceRef": {
                      "Entity": "protheus_pedidosVendas"
                    }
                  },
                  "Property": "ATC Participacao Estado %"
                }
              },
              "queryRef": "protheus_pedidosVendas.ATC Participacao Estado %",
              "nativeQueryRef": "ATC Participacao Estado %"
            }
          ]
        }
      },
      "sortDefinition": {
        "sort": [
          {
            "field": {
              "Measure": {
                "Expression": {
                  "SourceRef": {
                    "Entity": "protheus_pedidosVendas"
                  }
                },
                "Property": "ATC Participacao Estado %"
              }
            },
            "direction": "Descending"
          }
        ]
      }
    },
    "drillFilterOtherVisuals": true
  }
}